threader3000.py
threader3000-1.0.7.dist-info/entry_points.txt
threader3000-1.0.7.dist-info/WHEEL
threader3000-1.0.7.dist-info/METADATA
threader3000-1.0.7.dist-info/RECORD
