Metadata-Version: 2.1
Name: threader3000
Version: 1.0.7
Summary: Threader3000 - Multi-threaded Port Scanner
Home-page: https://github.com/dievus/threader3000
Keywords: port scanner, port, scanner
Author: The Mayor
Requires-Python: >=3.5,<4.0
Classifier: Programming Language :: Python :: 3
Classifier: Programming Language :: Python :: 3.5
Classifier: Programming Language :: Python :: 3.6
Classifier: Programming Language :: Python :: 3.7
Classifier: Programming Language :: Python :: 3.8
Project-URL: Issues Tracker, https://github.com/dievus/threader3000/issues
Project-URL: Website, https://www.cybersecpadawan.com
